{
  "project_info": {
    "project_number": "385964336088",
    "project_id": "ecommerce-dc0cb",
    "storage_bucket": "ecommerce-dc0cb.appspot.com"
  },
  "client": [
    {
      "client_info": {
        "mobilesdk_app_id": "1:385964336088:android:067bd730e049d7129bc8ad",
        "android_client_info": {
          "package_name": "com.aniket.ecommerce"
        }
      },
      "oauth_client": [
        {
          "client_id": "385964336088-eeed89jd51bvjav0fhmf7h3s47ancbvn.apps.googleusercontent.com",
          "client_type": 3
        }
      ],
      "api_key": [
        {
          "current_key": "AIzaSyDXdoEgmRrl55vCTmjPPGDaN8Zh3owxXnI"
        }
      ],
      "services": {
        "appinvite_service": {
          "other_platform_oauth_client": [
            {
              "client_id": "385964336088-eeed89jd51bvjav0fhmf7h3s47ancbvn.apps.googleusercontent.com",
              "client_type": 3
            }
          ]
        }
      }
    }
  ],
  "configuration_version": "1"
}